mod1/__init__.py
mod1/add.py
mod1/submod/__init__.py
mod1/submod/multi.py
mod2/__init__.py
mod2/sub.py
cdreek_algorithms-0.0.1.dist-info/METADATA
cdreek_algorithms-0.0.1.dist-info/WHEEL
cdreek_algorithms-0.0.1.dist-info/top_level.txt
cdreek_algorithms-0.0.1.dist-info/RECORD
